moody/__init__.py
moody/bussen.py
moody/conf.py
moody/contracttool.py
moody/erc20.py
moody/exceptions.py
moody/libeb.py
moody/paths.py
moody/artifacts/Proxy.abi
moody/artifacts/Proxy.bin
moody/artifacts/Proxy.bin-runtime
moody/artifacts/ProxyAdmin.abi
moody/artifacts/ProxyAdmin.bin
moody/artifacts/ProxyAdmin.bin-runtime
moody/artifacts/ProxyAdmin_meta.json
moody/artifacts/Proxy_meta.json
moody/artifacts/TransparentUpgradeableProxy.abi
moody/artifacts/TransparentUpgradeableProxy.bin
moody/artifacts/TransparentUpgradeableProxy.bin-runtime
moody/artifacts/TransparentUpgradeableProxy_meta.json
moody/artifacts/WETH9.abi
moody/artifacts/WETH9.bin
moody/artifacts/WETH9.bin-runtime
moody/artifacts/WETH9_meta.json
moody/artifacts/WRSC.abi
moody/artifacts/WRSC.bin
moody/artifacts/WRSC.bin-runtime
moody/artifacts/WRSC_meta.json
moody/bridge/__init__.py
moody/bridge/common.py
moody/buildercompile/__init__.py
moody/buildercompile/remotecompile.py
moody/buildercompile/transpile.py
moody/bulk/__init__.py
moody/bulk/basec.py
moody/flashbots/__init__.py
moody/flashbots/builder.py
moody/flashbots/flashbots.py
moody/flashbots/middleware.py
moody/flashbots/provider.py
moody/flashbots/types.py
moody/m/__init__.py
moody/m/bases.py
moody/m/tx_params.py
moody/m/b_send/__init__.py
moody/m/b_send/basec.py
moody/m/b_send/looper.py
moody/m/b_send2/__init__.py
moody/m/beri_coin/__init__.py
moody/m/blockhash_store/__init__.py
moody/m/c_token/__init__.py
moody/m/deposit_contract/__init__.py
moody/m/erc20/__init__.py
moody/m/eth2_multi_deposit/__init__.py
moody/m/kyc/__init__.py
moody/m/kyc/merkletree.py
moody/m/layer_zero_u_s_d_t/__init__.py
moody/m/multicall/__init__.py
moody/m/multicall/execute.py
moody/m/multicall2/__init__.py
moody/m/multicall2/execute.py
moody/m/multicall3/__init__.py
moody/m/multicall3/call.py
moody/m/multicall3/constants.py
moody/m/multicall3/eth_retry.py
moody/m/multicall3/exceptions.py
moody/m/multicall3/loggers.py
moody/m/multicall3/multicall.py
moodyeth-4.60.dist-info/LICENSE
moodyeth-4.60.dist-info/METADATA
moodyeth-4.60.dist-info/WHEEL
moodyeth-4.60.dist-info/top_level.txt
moodyeth-4.60.dist-info/RECORD
