Metadata-Version: 2.1
Name: moodyeth
Version: 4.60
Summary: A Python API for interacting with Ethereum based networks
Home-page: https://github.com/tokenchain/moodyeth
Author: Heskemo
Author-email: topdog@onekexx.com
License: MIT License
Keywords: ethereum eth-api eth-api-python eth-base cli sdk pentest
Classifier: Development Status :: 3 - Alpha
Classifier: Intended Audience :: Developers
Classifier: License :: OSI Approved :: MIT License
Classifier: Natural Language :: English
Classifier: Topic :: Software Development :: Code Generators
Classifier: Topic :: Software Development :: Libraries :: Python Modules
Classifier: Programming Language :: Python :: 3.9
Classifier: Programming Language :: Python :: 3.11
Classifier: Programming Language :: Python :: 3.12
Requires-Python: >=3.8,<4
License-File: LICENSE
Requires-Dist: mypy-extensions ==0.4.3
Requires-Dist: web3 >=5.20.0
Requires-Dist: eth-utils ==1.10.0
Requires-Dist: eth-uniswap ==0.0.2
Provides-Extra: dev
Requires-Dist: coverage ; extra == 'dev'
Requires-Dist: pep8 ; extra == 'dev'
Requires-Dist: pyflakes ; extra == 'dev'
Requires-Dist: pylint ; extra == 'dev'
Requires-Dist: pytest-cov ; extra == 'dev'
Requires-Dist: mock ; extra == 'dev'
Requires-Dist: sphinx-better-theme >=0.1.4 ; extra == 'dev'
Requires-Dist: click >=5.1 ; extra == 'dev'
Requires-Dist: configparser ==3.5.0 ; extra == 'dev'
Requires-Dist: contextlib2 >=0.5.4 ; extra == 'dev'
Requires-Dist: py-solc >=0.4.0 ; extra == 'dev'
Requires-Dist: pytest >=2.7.2 ; extra == 'dev'
Requires-Dist: sphinx ; extra == 'dev'
Requires-Dist: pdoc3 ; extra == 'dev'
Requires-Dist: sphinx-rtd-theme >=0.1.9 ; extra == 'dev'
Requires-Dist: toposort >=1.4 ; extra == 'dev'
Requires-Dist: urllib3 ; extra == 'dev'
Requires-Dist: wheel >=0.31.0 ; extra == 'dev'
Requires-Dist: bumpversion ; extra == 'dev'
Requires-Dist: flaky >=3.3.0 ; extra == 'dev'
Requires-Dist: hypothesis >=3.31.2 ; extra == 'dev'
Requires-Dist: pytest <4,>=3.5.0 ; extra == 'dev'
Requires-Dist: pytest-mock ==1.* ; extra == 'dev'
Requires-Dist: pytest-pythonpath >=0.3 ; extra == 'dev'
Requires-Dist: pytest-watch ==4.* ; extra == 'dev'
Requires-Dist: pytest-xdist ==1.* ; extra == 'dev'
Requires-Dist: setuptools >=38.6.0 ; extra == 'dev'
Requires-Dist: tox >=1.8.0 ; extra == 'dev'
Requires-Dist: twine >=1.11.0 ; extra == 'dev'
Requires-Dist: tqdm ; extra == 'dev'
Requires-Dist: pyinstall ; extra == 'dev'
Requires-Dist: when-changed ; extra == 'dev'
Provides-Extra: docs
Requires-Dist: mock ; extra == 'docs'
Requires-Dist: sphinx-better-theme >=0.1.4 ; extra == 'docs'
Requires-Dist: click >=5.1 ; extra == 'docs'
Requires-Dist: configparser ==3.5.0 ; extra == 'docs'
Requires-Dist: contextlib2 >=0.5.4 ; extra == 'docs'
Requires-Dist: py-solc >=0.4.0 ; extra == 'docs'
Requires-Dist: pytest >=2.7.2 ; extra == 'docs'
Requires-Dist: sphinx ; extra == 'docs'
Requires-Dist: pdoc3 ; extra == 'docs'
Requires-Dist: sphinx-rtd-theme >=0.1.9 ; extra == 'docs'
Requires-Dist: toposort >=1.4 ; extra == 'docs'
Requires-Dist: urllib3 ; extra == 'docs'
Requires-Dist: wheel >=0.31.0 ; extra == 'docs'
Provides-Extra: tester
Requires-Dist: coverage ; extra == 'tester'
Requires-Dist: pep8 ; extra == 'tester'
Requires-Dist: pyflakes ; extra == 'tester'
Requires-Dist: pylint ; extra == 'tester'
Requires-Dist: pytest-cov ; extra == 'tester'
